ibf/__init__.py
ibf/inputoutput.py
ibf/interpreter.py
ibf/tokenizer.py
ibf-0.1.data/data/man/man1/ibf.1
ibf-0.1.data/scripts/ibf
ibf-0.1.dist-info/METADATA
ibf-0.1.dist-info/RECORD
ibf-0.1.dist-info/WHEEL
ibf-0.1.dist-info/top_level.txt
