Metadata-Version: 2.1
Name: ibf
Version: 0.1
Summary: An interactive BrainFuck interpreter
Home-page: https://github.com/mathialo/interactive-brainfuck
Author: Mathias Lohne
Author-email: mathialo@ifi.uio.no
License: MIT
Platform: UNKNOWN
Requires-Dist: argparse
Requires-Dist: readline
Requires-Dist: numpy
